delegateto.py
delegateto-1.3.dist-info/LICENSE
delegateto-1.3.dist-info/METADATA
delegateto-1.3.dist-info/WHEEL
delegateto-1.3.dist-info/top_level.txt
delegateto-1.3.dist-info/RECORD
