Metadata-Version: 2.1
Name: delegateto
Version: 1.3
Summary: UNKNOWN
Home-page: UNKNOWN
Author: Daniel Hilst Selli
Author-email: danielhilst@gmail.com
License: Apache-2.0
Platform: UNKNOWN
Requires-Python: >=3
